juphelp/__init__.py
juphelp/helper.py
juphelp-0.1.0.dist-info/METADATA
juphelp-0.1.0.dist-info/WHEEL
juphelp-0.1.0.dist-info/entry_points.txt
juphelp-0.1.0.dist-info/top_level.txt
juphelp-0.1.0.dist-info/RECORD
