Metadata-Version: 2.1
Name: juphelp
Version: 0.1.0
Requires-Dist: requests
